flowflops/__init__.py
flowflops/flow_counter.py
flowflops/flow_engine.py
flowflops/flow_ops.py
flowflops/utils.py
tests/__init__.py
tests/test_delta_between_graph_eager.py
tests/test_layers.py
flowflops-0.0.1.post2211300851.dist-info/METADATA
flowflops-0.0.1.post2211300851.dist-info/WHEEL
flowflops-0.0.1.post2211300851.dist-info/top_level.txt
flowflops-0.0.1.post2211300851.dist-info/zip-safe
flowflops-0.0.1.post2211300851.dist-info/RECORD
