Metadata-Version: 2.1
Name: flowflops
Version: 0.0.1-2211300851
Summary: A tool to count the FLOPs of OneFlow model.
Home-page: 
Author: OneFlow
Author-email: 
License: Apache 2.0
Classifier: Programming Language :: Python :: 3
Classifier: License :: OSI Approved :: Apache Software License
Classifier: Operating System :: OS Independent
